Metadata-Version: 2.1
Name: aa-probability
Version: 1.0
Summary: Gaussian and Binomial distributions
Home-page: UNKNOWN
Author: bigdateros
Author-email: aalvarez@bigdateros.com
License: UNKNOWN
Platform: UNKNOWN
